setup.py
smartcache/__init__.py
smartcache/commands.py
smartcache/object_cache.py
smartcache/redis_cache.py
smartcache.egg-info/PKG-INFO
smartcache.egg-info/SOURCES.txt
smartcache.egg-info/dependency_links.txt
smartcache.egg-info/top_level.txt
smartcache/test/__init__.py
smartcache/test/object_cache_test.py
smartcache/test/redis_cache_test.py
smartcache/test/runtests.py
smartcache/test/util.py