Metadata-Version: 1.0
Name: smartcache
Version: 0.0.2
Summary: smartcache is friendly redis api
Home-page: http://github.com/wecatch/smartcache
Author: Wecatch.me
Author-email: wecatch.me@gmail.com
License: http://www.apache.org/licenses/LICENSE-2.0
Platform: UNKNOWN
